{
"meta":{"test_sets":[],"test_metrics":[],"learn_metrics":[{"best_value":"Min","name":"Logloss"}],"launch_mode":"Train","parameters":"","iteration_count":100,"learn_sets":["learn"],"name":"experiment"},
"iterations":[
{"learn":[0.6560798892],"iteration":0,"passed_time":0.01450784218,"remaining_time":1.436276376},
{"learn":[0.6284920098],"iteration":1,"passed_time":0.02167355899,"remaining_time":1.062004391},
{"learn":[0.6004488602],"iteration":2,"passed_time":0.02665543143,"remaining_time":0.8618589496},
{"learn":[0.5758148049],"iteration":3,"passed_time":0.03091891523,"remaining_time":0.7420539654},
{"learn":[0.555711996],"iteration":4,"passed_time":0.03486350556,"remaining_time":0.6624066057},
{"learn":[0.5355979344],"iteration":5,"passed_time":0.03830648584,"remaining_time":0.6001349449},
{"learn":[0.5178443425],"iteration":6,"passed_time":0.04144598554,"remaining_time":0.5506395222},
{"learn":[0.501158213],"iteration":7,"passed_time":0.04449611925,"remaining_time":0.5117053713},
{"learn":[0.4873046115],"iteration":8,"passed_time":0.04756020243,"remaining_time":0.4808864912},
{"learn":[0.4759933171],"iteration":9,"passed_time":0.04974779585,"remaining_time":0.4477301626},
{"learn":[0.4643040915],"iteration":10,"passed_time":0.05244028224,"remaining_time":0.4242895563},
{"learn":[0.4567407081],"iteration":11,"passed_time":0.05382619072,"remaining_time":0.3947253986},
{"learn":[0.4473741094],"iteration":12,"passed_time":0.055757605,"remaining_time":0.3731470488},
{"learn":[0.4365231849],"iteration":13,"passed_time":0.05877455841,"remaining_time":0.361043716},
{"learn":[0.4262476809],"iteration":14,"passed_time":0.06184944038,"remaining_time":0.3504801622},
{"learn":[0.4179487636],"iteration":15,"passed_time":0.06514151708,"remaining_time":0.3419929647},
{"learn":[0.4086210299],"iteration":16,"passed_time":0.06857525752,"remaining_time":0.3348086103},
{"learn":[0.4010337849],"iteration":17,"passed_time":0.07173688593,"remaining_time":0.3268013693},
{"learn":[0.3936162552],"iteration":18,"passed_time":0.07485359023,"remaining_time":0.3191126741},
{"learn":[0.3879410565],"iteration":19,"passed_time":0.0779354786,"remaining_time":0.3117419144},
{"learn":[0.3808730469],"iteration":20,"passed_time":0.0812019631,"remaining_time":0.3054740517},
{"learn":[0.3767862],"iteration":21,"passed_time":0.08441324805,"remaining_time":0.299283334},
{"learn":[0.3712364331],"iteration":22,"passed_time":0.08748628717,"remaining_time":0.2928888744},
{"learn":[0.3653028435],"iteration":23,"passed_time":0.09064259313,"remaining_time":0.2870348783},
{"learn":[0.360672208],"iteration":24,"passed_time":0.09373346856,"remaining_time":0.2812004057},
{"learn":[0.3558175216],"iteration":25,"passed_time":0.09727543135,"remaining_time":0.2768608431},
{"learn":[0.3504180241],"iteration":26,"passed_time":0.1004263793,"remaining_time":0.2715231737},
{"learn":[0.3452171388],"iteration":27,"passed_time":0.1035432175,"remaining_time":0.2662539878},
{"learn":[0.3412614654],"iteration":28,"passed_time":0.1066914003,"remaining_time":0.2612099801},
{"learn":[0.3383344206],"iteration":29,"passed_time":0.1098119831,"remaining_time":0.2562279606},
{"learn":[0.3345746557],"iteration":30,"passed_time":0.1134888144,"remaining_time":0.2526041352},
{"learn":[0.3307747044],"iteration":31,"passed_time":0.11663693,"remaining_time":0.2478534763},
{"learn":[0.32604851],"iteration":32,"passed_time":0.1197931865,"remaining_time":0.2432164696},
{"learn":[0.3226282027],"iteration":33,"passed_time":0.1231060696,"remaining_time":0.2389706058},
{"learn":[0.3211170928],"iteration":34,"passed_time":0.1242775491,"remaining_time":0.2308011626},
{"learn":[0.3173873099],"iteration":35,"passed_time":0.1279681737,"remaining_time":0.2274989755},
{"learn":[0.3134033449],"iteration":36,"passed_time":0.1315868814,"remaining_time":0.2240533386},
{"learn":[0.3110701993],"iteration":37,"passed_time":0.1347318685,"remaining_time":0.2198256803},
{"learn":[0.3080349504],"iteration":38,"passed_time":0.1378621956,"remaining_time":0.2156306137},
{"learn":[0.3054912128],"iteration":39,"passed_time":0.1409900576,"remaining_time":0.2114850864},
{"learn":[0.3051683351],"iteration":40,"passed_time":0.1416530895,"remaining_time":0.2038422507},
{"learn":[0.3035363424],"iteration":41,"passed_time":0.1452269703,"remaining_time":0.2005515304},
{"learn":[0.3011663891],"iteration":42,"passed_time":0.1484470039,"remaining_time":0.1967785866},
{"learn":[0.297816444],"iteration":43,"passed_time":0.1515237488,"remaining_time":0.1928484075},
{"learn":[0.2951210078],"iteration":44,"passed_time":0.1546463478,"remaining_time":0.1890122028},
{"learn":[0.2937904621],"iteration":45,"passed_time":0.1560708045,"remaining_time":0.1832135531},
{"learn":[0.2907567134],"iteration":46,"passed_time":0.1605165143,"remaining_time":0.1810079843},
{"learn":[0.2888489566],"iteration":47,"passed_time":0.1638071849,"remaining_time":0.1774577836},
{"learn":[0.2868010308],"iteration":48,"passed_time":0.1668871782,"remaining_time":0.1736988997},
{"learn":[0.2844249797],"iteration":49,"passed_time":0.1698956634,"remaining_time":0.1698956634},
{"learn":[0.2821493154],"iteration":50,"passed_time":0.1734802358,"remaining_time":0.1666770893},
{"learn":[0.2792490071],"iteration":51,"passed_time":0.1766259074,"remaining_time":0.1630392992},
{"learn":[0.2764026544],"iteration":52,"passed_time":0.1797463102,"remaining_time":0.1593976713},
{"learn":[0.2746788729],"iteration":53,"passed_time":0.1828002802,"remaining_time":0.1557187572},
{"learn":[0.2727534436],"iteration":54,"passed_time":0.1858677207,"remaining_time":0.1520735897},
{"learn":[0.2721076164],"iteration":55,"passed_time":0.1865607017,"remaining_time":0.1465834084},
{"learn":[0.2706633325],"iteration":56,"passed_time":0.1902112807,"remaining_time":0.1434927205},
{"learn":[0.268922746],"iteration":57,"passed_time":0.1938735008,"remaining_time":0.1403911557},
{"learn":[0.2669287628],"iteration":58,"passed_time":0.1973132359,"remaining_time":0.1371159775},
{"learn":[0.264616779],"iteration":59,"passed_time":0.2005819616,"remaining_time":0.1337213078},
{"learn":[0.2633035473],"iteration":60,"passed_time":0.2041310258,"remaining_time":0.1305100001},
{"learn":[0.2602509121],"iteration":61,"passed_time":0.2075795552,"remaining_time":0.127226179},
{"learn":[0.2575984403],"iteration":62,"passed_time":0.2112414309,"remaining_time":0.1240624277},
{"learn":[0.2555700069],"iteration":63,"passed_time":0.214528879,"remaining_time":0.1206724945},
{"learn":[0.2532064427],"iteration":64,"passed_time":0.2180122444,"remaining_time":0.1173912085},
{"learn":[0.2511359997],"iteration":65,"passed_time":0.2215618702,"remaining_time":0.1141379332},
{"learn":[0.2489202999],"iteration":66,"passed_time":0.2247632626,"remaining_time":0.1107042935},
{"learn":[0.2472597187],"iteration":67,"passed_time":0.2278424158,"remaining_time":0.1072199604},
{"learn":[0.2454097268],"iteration":68,"passed_time":0.230892514,"remaining_time":0.1037343179},
{"learn":[0.243690131],"iteration":69,"passed_time":0.2355098394,"remaining_time":0.1009327883},
{"learn":[0.2417775424],"iteration":70,"passed_time":0.2385387283,"remaining_time":0.09743131155},
{"learn":[0.2403117543],"iteration":71,"passed_time":0.2415100553,"remaining_time":0.09392057707},
{"learn":[0.2392262815],"iteration":72,"passed_time":0.244556665,"remaining_time":0.09045246513},
{"learn":[0.2384324306],"iteration":73,"passed_time":0.2476016168,"remaining_time":0.08699516266},
{"learn":[0.2368178282],"iteration":74,"passed_time":0.2522423965,"remaining_time":0.08408079884},
{"learn":[0.234768649],"iteration":75,"passed_time":0.2552434882,"remaining_time":0.08060320679},
{"learn":[0.2333874341],"iteration":76,"passed_time":0.2582129257,"remaining_time":0.07712853624},
{"learn":[0.2310822074],"iteration":77,"passed_time":0.2612837591,"remaining_time":0.07369541925},
{"learn":[0.2296494878],"iteration":78,"passed_time":0.265850418,"remaining_time":0.07066909844},
{"learn":[0.227328699],"iteration":79,"passed_time":0.268863654,"remaining_time":0.0672159135},
{"learn":[0.2261145328],"iteration":80,"passed_time":0.2718511728,"remaining_time":0.06376755906},
{"learn":[0.2246811807],"iteration":81,"passed_time":0.2749453773,"remaining_time":0.06035386331},
{"learn":[0.2236141971],"iteration":82,"passed_time":0.2780611732,"remaining_time":0.05695228849},
{"learn":[0.2213849565],"iteration":83,"passed_time":0.2814760806,"remaining_time":0.05361449155},
{"learn":[0.2184836325],"iteration":84,"passed_time":0.2846597755,"remaining_time":0.05023407804},
{"learn":[0.2166906573],"iteration":85,"passed_time":0.2876760673,"remaining_time":0.04683098769},
{"learn":[0.2162238148],"iteration":86,"passed_time":0.2891665029,"remaining_time":0.04320878779},
{"learn":[0.2150201186],"iteration":87,"passed_time":0.2910657214,"remaining_time":0.03969078019},
{"learn":[0.2140920764],"iteration":88,"passed_time":0.2944556133,"remaining_time":0.03639339041},
{"learn":[0.2122499261],"iteration":89,"passed_time":0.297650372,"remaining_time":0.03307226356},
{"learn":[0.2108527039],"iteration":90,"passed_time":0.3006700122,"remaining_time":0.02973659462},
{"learn":[0.2094570263],"iteration":91,"passed_time":0.3073781058,"remaining_time":0.02672853094},
{"learn":[0.2075687441],"iteration":92,"passed_time":0.3107459585,"remaining_time":0.02338948075},
{"learn":[0.2063191185],"iteration":93,"passed_time":0.314043031,"remaining_time":0.02004529985},
{"learn":[0.2041351804],"iteration":94,"passed_time":0.3172415593,"remaining_time":0.01669692417},
{"learn":[0.2020804375],"iteration":95,"passed_time":0.3203282356,"remaining_time":0.01334700982},
{"learn":[0.2003568083],"iteration":96,"passed_time":0.3241278204,"remaining_time":0.01002457176},
{"learn":[0.1978187872],"iteration":97,"passed_time":0.3275290567,"remaining_time":0.006684266463},
{"learn":[0.196220527],"iteration":98,"passed_time":0.3310079546,"remaining_time":0.003343514693},
{"learn":[0.1948036947],"iteration":99,"passed_time":0.3341408212,"remaining_time":0}
]}